filemeta/__init__.py
filemeta/cli.py
filemeta/database.py
filemeta/metadata_manager.py
filemeta/models.py
filemeta/utils.py
pranavik928_filemeta-0.1.0.dist-info/METADATA
pranavik928_filemeta-0.1.0.dist-info/WHEEL
pranavik928_filemeta-0.1.0.dist-info/entry_points.txt
pranavik928_filemeta-0.1.0.dist-info/top_level.txt
pranavik928_filemeta-0.1.0.dist-info/RECORD
