Metadata-Version: 2.4
Name: pranavik928-filemeta
Version: 0.1.0
Summary: A CLI tool for managing server file metadata.
Home-page: https://github.com/yourusername/filemeta_project
Author: Your Name
Author-email: your.email@example.com
Classifier: Programming Language :: Python :: 3
Classifier: License :: OSI Approved :: MIT License
Classifier: Operating System :: OS Independent
Requires-Python: >=3.7
Requires-Dist: SQLAlchemy
Requires-Dist: Click
Requires-Dist: psycopg2-binary
Dynamic: author
Dynamic: author-email
Dynamic: classifier
Dynamic: description-content-type
Dynamic: home-page
Dynamic: requires-dist
Dynamic: requires-python
Dynamic: summary
